<?xml version="1.0" encoding="ISO-8859-1"?>
<message_catalog package_key="intranet-cost" package_version="3.4.0.6.0" locale="es_LA" charset="ISO-8859-1">

  <msg key="Absences">Ausencias</msg>
  <msg key="Accounts_Payable">Cuentas a Pagar</msg>
  <msg key="Accounts_Receivable">Cuentas a Cobrar</msg>
  <msg key="Admin">Admin</msg>
  <msg key="Administration">Administración</msg>
  <msg key="All_Costs">Todos los Costos</msg>
  <msg key="Amount">Monto</msg>
  <msg key="Client">Cliente</msg>
  <msg key="Companies">Empresas</msg>
  <msg key="Company">Empresa</msg>
  <msg key="context">Contexto</msg>
  <msg key="Cost_Center">Centro de Costos</msg>
  <msg key="Cost_Centers">Centros de Costos</msg>
  <msg key="Cost_Items">Elementos de costo</msg>
  <msg key="CostCenter_short">CC</msg>
  <msg key="create">crear</msg>
  <msg key="Currency">Moneda</msg>
  <msg key="Customer">Cliente</msg>
  <msg key="Customer_Invoices">Facturas a Clientes</msg>
  <msg key="Customer_Links">Links de cliente</msg>
  <msg key="Customers">Clientes</msg>
  <msg key="Del">Borrar</msg>
  <msg key="Description">Descripción</msg>
  <msg key="Document">Documento</msg>
  <msg key="Document_Status">Status de Documento</msg>
  <msg key="Document_Type">Tipo de Documento</msg>
  <msg key="Documentation">Documentación:</msg>
  <msg key="Due">Vencimiento</msg>
  <msg key="Due_Date">Fecha de Vencimiento</msg>
  <msg key="Edit_Cost">Editar Costo</msg>
  <msg key="Effective_Date">Fecha efectiva</msg>
  <msg key="Expenses">Gastos</msg>
  <msg key="Export_Finance_to_CSV">Exportar a CSV</msg>
  <msg key="Filter_Documents">Filtrar Documentos</msg>
  <msg key="Finance">Finanzas</msg>
  <msg key="finance">finanzas</msg>
  <msg key="Finance_Home">Portada de Finanzas</msg>
  <msg key="Finance_Summary">Resumen de Finanzas</msg>
  <msg key="Financial_Documents">Documentos financieros</msg>
  <msg key="Financial_Summary">Resumen financiero</msg>
  <msg key="Go">Ir</msg>
  <msg key="Grand_Total">Total</msg>
  <msg key="Investment">Inversión</msg>
  <msg key="lt_Cost_Item_Administrat">Administración de elementos de costo</msg>
  <msg key="lt_Create_a_new_purchase">Crear nueva orden de compra</msg>
  <msg key="lt_Didnt_find_the_the_vi">No se ha encontrado la vista '%$view_name%'</msg>
  <msg key="lt_Distribute_costs_acco">Distribuir costos de acuerdo a la información de la hoja de tiempos</msg>
  <msg key="lt_Finance_high-level_de">Finanzas descripción de alto nivel</msg>
  <msg key="lt_No_financial_document">No existen aún documentos financieros para este proyecto</msg>
  <msg key="lt_There_are_currently_n">Actualmente no existen costos que se ajusten a los criterios seleccionados</msg>
  <msg key="lt_This_is_the_homepage_">Esta es la portada del &quot;Area Financiera&quot;. Aquí podrá encontrar e introducir toda la informaciín sobre empresas, proyectos y usuarios.</msg>
  <msg key="Materials_Service_Types">Materiales (Tipos de Servicio)</msg>
  <msg key="more_costs">mas costos...</msg>
  <msg key="Multiple_Currency_Warning">&lt;h2&gt;Advertencia de Divisa Múltiple&lt;/h2&gt; &lt;p&gt; Este proyecto contiene documentos financieros en más de una moneda. &lt;br&gt; Aunque es correcto en general, esto impide calcular el resultado de pérdidas y ganancias e incluírlo en el cálculo del margen de proyecto&lt;/p&gt;</msg>
  <msg key="Name">Nombre</msg>
  <msg key="New_Cost">Nuevo Costo</msg>
  <msg key="New_Cost_Item">Nuevo Elemento de Costos</msg>
  <msg key="New_Customer_Docs">Crear Nuevo Documento de Cliente</msg>
  <msg key="New_Customer_Invoices_Quotes">Nueva Factura a Cliente &amp; Cotización</msg>
  <msg key="New_Provider_Bills_POs">Nueva Factura de Proveedor &amp; Orden de Compra</msg>
  <msg key="New_Provider_Docs">Crear Nuevo Documento de Proveedor</msg>
  <msg key="New_Timesheet_Invoice">Nueva Factura basada en Hoja de Tiempos</msg>
  <msg key="New_Trans_Invoice">Nueva factura de traducción</msg>
  <msg key="Next_Page">Próxima Página</msg>
  <msg key="Note">Nota</msg>
  <msg key="Options">Opciones:</msg>
  <msg key="Org_Amount">Org</msg>
  <msg key="Outdated_Message">Advertencia de tipos de cambio desactualizados</msg>
  <msg key="Outdated_since_x_days">Desactualizados desde %days% días</msg>
  <msg key="Paid">Pago</msg>
  <msg key="Paid_Amount">Monto Pago</msg>
  <msg key="Paid_Currency">Moneda Pago</msg>
  <msg key="Payment_Days">Días de PAgo</msg>
  <msg key="Payments">Pagos</msg>
  <msg key="Please_Select">Por favor seleccione</msg>
  <msg key="Preliminary_Costs">Costos Preliminares</msg>
  <msg key="Preliminary_Total">Total Preliminar</msg>
  <msg key="Previous_Page">Página Anterior</msg>
  <msg key="Print_Template">Plantilla de impresión</msg>
  <msg key="Project">Proyecto</msg>
  <msg key="Provider">Proveedor</msg>
  <msg key="Provider_Bills">Facturas de Proveedor</msg>
  <msg key="Provider_Links">Links de Proveedor</msg>
  <msg key="Providers">Proveedores</msg>
  <msg key="Purchase_Orders">Ordenes de Compra</msg>
  <msg key="Quotes">Cotizaciones</msg>
  <msg key="Real_Costs">Costos Reales</msg>
  <msg key="Repeating_Costs">Costos Repetitivos</msg>
  <msg key="Save">Guardar</msg>
  <msg key="Start_Block">Inicio de Bloque</msg>
  <msg key="Status">Status</msg>
  <msg key="TAX">IMPUESTOS</msg>
  <msg key="The_exchange_rates_are_outdated">Los tipos de camcio para las siguiente monedas están desactualizados. Por favor contacte al administrador del sistema para actualizarlos:</msg>
  <msg key="Timesheet_Budget">Presupuesto Hoja de Tiempos</msg>
  <msg key="Timesheet_Costs">Costos Hoja de Tiempos</msg>
  <msg key="Type">Tipo</msg>
  <msg key="VAT">IVA</msg>
  <msg key="Who_gets_the_money">Responsable de Cobranza</msg>
  <msg key="Who_pays">Responsable de Pago</msg>
</message_catalog>
