<?xml version="1.0" encoding="ISO-8859-1"?>
<message_catalog package_key="search" package_version="5.1.5" locale="es_ES" charset="ISO-8859-1">

  <msg key="________Search_took">. Tiempo empleado en la búsqueda</msg>
  <msg key="Advanced_Search">Búsqueda ampliada</msg>
  <msg key="advanced_search">&quot;búsqueda ampliada&quot;</msg>
  <msg key="anytime">todo</msg>
  <msg key="Date_Range">Intervalo temporal</msg>
  <msg key="details">detalles</msg>
  <msg key="Feeling_Lucky">Voy a Tener Suerte</msg>
  <msg key="lt_bstopwordsb_is_a_very">&quot;&lt;b&gt;%stopwords%&lt;/b&gt;&quot; es una palabra muy corriente, por lo que no la hemos incluido en su búsqueda.</msg>
  <msg key="lt_FtsEngineDriver_not_a">¡FtsEngineDriver no está disponible!</msg>
  <msg key="lt_Make_sure_all_words_a">Asegúrese de que todas las palabras están escritas correctamente.</msg>
  <msg key="lt_No_pages_were_found_c">No se han hallado páginas que contengan &quot;</msg>
  <msg key="lt_The_following_words_a">Las palabras siguientes son muy corrientes y no han sido incluidas en su búsqueda:</msg>
  <msg key="lt_Tip_In_most_browsers_">Consejo práctico: En la mayoría de buscadores basta con que pulse Intro en lugar de hacer clic sobre el botón de Búsqueda.</msg>
  <msg key="lt_Try_different_keyword">Intente con diferentes términos de búsqueda.</msg>
  <msg key="lt_Try_more_general_keyw">Intente con unos términos más generales.</msg>
  <msg key="lt_Try_your_query_on_stw">Intente su búsqueda con: %stw;noquote%</msg>
  <msg key="lt_You_must_specify_some">Debe especificar algunos términos de búsqueda.</msg>
  <msg key="nbspDisplay">&amp;nbsp;Mostrar</msg>
  <msg key="Next">Siguiente</msg>
  <msg key="of_about">de aprox.</msg>
  <msg key="past_3_months">pasados 3 meses</msg>
  <msg key="past_6_months">pasados 6 meses</msg>
  <msg key="past_year">pasado año</msg>
  <msg key="Previous">Anteriores</msg>
  <msg key="Result_page">Página de resultados:</msg>
  <msg key="Results">Resultados</msg>
  <msg key="results">resultados</msg>
  <msg key="Search">Búsqueda</msg>
  <msg key="Searched_for_query">Ha buscado por: %query%</msg>
  <msg key="seconds">segundos.</msg>
  <msg key="selected">seleccionados</msg>
  <msg key="Suggestions">Sugerencias:</msg>
  <msg key="The">El operador &quot;&lt;b&gt;AND&lt;/b&gt;&quot; no es necesario, ya que incluimos todos los términos de búsqueda por defecto.</msg>
  <msg key="Try_fewer_keywords">Intentes con menos términos de búsqueda.</msg>
  <msg key="Untitled">Sin título</msg>
</message_catalog>
