<?xml version="1.0" encoding="ISO-8859-1"?>
<message_catalog package_key="intranet-timesheet2" package_version="3.4.0.7.0" locale="de_DE" charset="ISO-8859-1">

  <msg key="1_Euro_equals">1 Euro entspricht</msg>
  <msg key="_user_id">und die Projekt ID kann bereit gestellt werden. Aber es gab einige Probleme mit ihnen...</msg>
  <msg key="A">A</msg>
  <msg key="Absence">Abwesehnheit</msg>
  <msg key="Absence_Type">Abwesenheitstyp</msg>
  <msg key="Absence_Type_1">Abwesenheitstyp</msg>
  <msg key="Absences">Abwesenheiten</msg>
  <msg key="absences">Abwesenheiten</msg>
  <msg key="Absent">Abwesend</msg>
  <msg key="Absent_1">Abwesend</msg>
  <msg key="Add_a_new_Absence">Neue Abwesenheit</msg>
  <msg key="Add_hours">Stunden erfassen</msg>
  <msg key="Add_lines">Neue Zeilen</msg>
  <msg key="Add_more_lines">Weitere Zeilen hinzufügen</msg>
  <msg key="Admin">Administration</msg>
  <msg key="Admin_Absences">Abwesenheiten verwalten</msg>
  <msg key="Administration">Administration</msg>
  <msg key="All">Alle</msg>
  <msg key="All_dates">Alle Tage</msg>
  <msg key="All_projects">Alle Projekte</msg>
  <msg key="all_the_companies">Alle Firmen</msg>
  <msg key="Amount_EUR">Betrag (EUR)</msg>
  <msg key="Amount_in_Euros">Betrag (EUR)</msg>
  <msg key="AMOUNTS">Beträge</msg>
  <msg key="and_absences_hours">und %absences_hours% Stunden Absenzen</msg>
  <msg key="Apply">Bestätigen</msg>
  <msg key="April">April</msg>
  <msg key="Associated_reports">Beteiligte Berichte</msg>
  <msg key="Aug">Aug</msg>
  <msg key="August">August</msg>
  <msg key="B">B</msg>
  <msg key="Bad_Absence">Fehlerhafte Abwesenheit</msg>
  <msg key="Based_on">Basierend auf</msg>
  <msg key="Billing_rate">Rate</msg>
  <msg key="Budget">Budget</msg>
  <msg key="C">C</msg>
  <msg key="Calendar">Kalender</msg>
  <msg key="Case">Fall</msg>
  <msg key="Casex">CASEX</msg>
  <msg key="Casex_for">CASEX für</msg>
  <msg key="Casex_Summary">CASEX Zusammenfassung</msg>
  <msg key="Category_Summaries">Zusammenfassungen Kategorien</msg>
  <msg key="Choose_project">Projekt wählen</msg>
  <msg key="Choose_projects_for_user">Projekte auswählen für  %user_name_from_search%</msg>
  <msg key="comma_separated">Komma separiert</msg>
  <msg key="Comp_VISA">Mit Kreditkarte bezahlt?</msg>
  <msg key="Companies">Firmen</msg>
  <msg key="Company">Firma</msg>
  <msg key="Contact">Kontakt</msg>
  <msg key="Contact_Info">Kontaktinformation</msg>
  <msg key="context">Kontext</msg>
  <msg key="Country">Land</msg>
  <msg key="Currency">Währung</msg>
  <msg key="D">D</msg>
  <msg key="Daily_project_notes">Tägliche Projektnotizen</msg>
  <msg key="Date">Datum</msg>
  <msg key="Date_for_user">%pretty_date% für %user_name_from_search%</msg>
  <msg key="Day">Tag</msg>
  <msg key="Day_of_Expense">Kostendatum</msg>
  <msg key="Day_of_week_Fri">Fr</msg>
  <msg key="Day_of_week_Mon">Mo</msg>
  <msg key="Day_of_week_Thu">Do</msg>
  <msg key="Day_of_week_Tue">Di</msg>
  <msg key="Day_of_week_Wed">Mi</msg>
  <msg key="DAYS">Tage</msg>
  <msg key="days">Tage</msg>
  <msg key="Dec">Dez</msg>
  <msg key="December">Dezember</msg>
  <msg key="Delete">Löschen</msg>
  <msg key="Description">Beschreibung</msg>
  <msg key="Deviation">Abweichung</msg>
  <msg key="Display">Anzeige</msg>
  <msg key="Display_Users">Benutzer anzeigen</msg>
  <msg key="Duration_days">Dauer in Tagen</msg>
  <msg key="Duration_days_help">Dauer in Tagen</msg>
  <msg key="E">E</msg>
  <msg key="Edit">Ändern</msg>
  <msg key="Edit_Absence">Abwesenheit bearbeiten</msg>
  <msg key="Employee">Mitarbeiter</msg>
  <msg key="End_Date">Enddatum</msg>
  <msg key="Ending">Ende</msg>
  <msg key="equals">ist gleich</msg>
  <msg key="Euro_Converter">Euro Konverter</msg>
  <msg key="Euro_converter">Euro Konverter</msg>
  <msg key="Eurocalculator">Euro Konverter</msg>
  <msg key="Excel_hour_report">Excel Stundenbericht</msg>
  <msg key="Expense_Code">Kostencode</msg>
  <msg key="Expense_Dedication">Kostenaufwand</msg>
  <msg key="F">F</msg>
  <msg key="February">Februar</msg>
  <msg key="Filter">Filter</msg>
  <msg key="Filter_Absences">Filter Abwesenheiten</msg>
  <msg key="Filter_Tasks">Aufgaben filtern</msg>
  <msg key="For_which_project">Für Projekt</msg>
  <msg key="Friday">Freitag</msg>
  <msg key="From">Von</msg>
  <msg key="from">Von</msg>
  <msg key="Future">Zukunft</msg>
  <msg key="G">G</msg>
  <msg key="Go">Los</msg>
  <msg key="go">los</msg>
  <msg key="Grand_Total">Gesamtsumme</msg>
  <msg key="H">H</msg>
  <msg key="here">hier</msg>
  <msg key="Hour_logging__Casex">Stunden Erfassung</msg>
  <msg key="Hours">Stunden</msg>
  <msg key="hours">Stunden</msg>
  <msg key="Hours_1">Stunden</msg>
  <msg key="Hours_by_user_name">Erfaßte Stunden von %user_name% </msg>
  <msg key="Hours_Dedication">Stundenaufwand</msg>
  <msg key="hours_spend_overall">alle erfaßten Stunden</msg>
  <msg key="Hours_Summary">Zusammenfassung Stunden</msg>
  <msg key="hours_units">%hours% Stunden</msg>
  <msg key="I">I</msg>
  <msg key="Internal_Comment">Interner Kommentar</msg>
  <msg key="J">J</msg>
  <msg key="January">Januar</msg>
  <msg key="July">July</msg>
  <msg key="Jun">Juni</msg>
  <msg key="June">Juni</msg>
  <msg key="K">K</msg>
  <msg key="L">L</msg>
  <msg key="Last_3_months">Letzte drei Monate</msg>
  <msg key="Local">Lokal</msg>
  <msg key="Log_Absences">Abwesenheiten melden</msg>
  <msg key="log_dedication">Stunden erfassen</msg>
  <msg key="Log_Hours">Stunden kontieren</msg>
  <msg key="log_hours">Stunden erfassen</msg>
  <msg key="Log_hours_for_user">Stunden für:</msg>
  <msg key="Log_your_hours">Erfassen sie ihre Stunden</msg>
  <msg key="lt_A_total_of_total_hour">Es wurden insgesamt %total_hours_str% Stunden auf diesem Projekt erfaßt.</msg>
  <msg key="lt_Add_hours_on_other_pr">Stunden erfassen auf anderen Projekten</msg>
  <msg key="lt_All_the_fields_should">Alle Felder müssen vorm verschicken ausgefüllt werden.</msg>
  <msg key="lt_All_the_fields_should_1">Alle Felder müssen vorm  %action% ausgefüllt sein.</msg>
  <msg key="lt_based_select_hours_pe">%based_select% Stunden pro Woche</msg>
  <msg key="lt_Choose_an_employee_to">Wählen sie einen Miterbeiter, um seine erfaßten Stunden zu sehen</msg>
  <msg key="lt_Click_me_for_download">Clicken sie hier um den Bericht als report.csv-Datei herunterzuladen</msg>
  <msg key="lt_Click_on_a_persons_na">Clicken sie auf eine Person, um die erfaßte Stunden anzuzeigen</msg>
  <msg key="lt_Click_on_a_project_na">Clicken sie auf ein Projekt um die erfaßten Stunden pro Person anzuzeigen</msg>
  <msg key="lt_Dedication_days_repor">Stundenbericht</msg>
  <msg key="lt_Dedication_Logging__C">Einsatz Protokollierung &amp;amp; CASEX von %user_name%</msg>
  <msg key="lt_Dedication_Logging__C_1">Einsatz Protokollierung &amp;amp; CASEX</msg>
  <msg key="lt_Dedication_logging_fo">Stundenerfassung für</msg>
  <msg key="lt_Description_field_is_">Textfeld ist zwingend erforderlich.</msg>
  <msg key="lt_Description_is_mandat">Beschreibung ist zwingend erforderlich. Bitte beschreiben Sie den Zweck der Kosten. Im Fall von &quot;Kilometer mit dem eigenen Auto&quot;, schreiben Sie auch die Anzahl der Kilometer. Der Betrag kann entweder mit einem &lt;B&gt;&quot;.&quot;&lt;/B&gt; (Amerikanisch) oder &lt;B&gt;&quot;,&quot;&lt;/B&gt; (Europäisch) für den Dezimalpunkt eingetragen werden</msg>
  <msg key="lt_Display_all_hours_on_">Zeige alle Stunden über alle Projekte an</msg>
  <msg key="lt_Error_in_project_entr">Fehler in Projekteintrag</msg>
  <msg key="lt_For_Vacation_Sickness">Für Urlaub, Krankheit und berufliche Weiterbildung, wählen Sie den Prozess Personal.</msg>
  <msg key="lt_For_Vacation_Sickness_1">Für Krankheit, Urlaub (Land, Region &amp; Stadt) und berufliche Weiterbildung, wählen Sie den Prozess Personal.</msg>
  <msg key="lt_Full_Time_Equivalents">Vollzeitäquivalente</msg>
  <msg key="lt_Go_back_to_where_you_">Gehen sie zurück von wo sie kommen</msg>
  <msg key="lt_Hour_logging__Casex_b">Stundenerfassung für %user_name% </msg>
  <msg key="lt_Hours_for_pretty_date">Stunden für %pretty_date% </msg>
  <msg key="lt_Hours_for_user_name_W">Stunden für $user_name (Der Woche vom %date_value%) </msg>
  <msg key="lt_hours_spend_on_projec">Erfaßte Stunden auf Projekt '%project_name%'</msg>
  <msg key="lt_hours_varof_those_uni">%hours_var% Diese Einheiten werden pro Stunde in Rechnung gestellt, für einen Gesamtbetrag von</msg>
  <msg key="lt_Insufficient_Privileg">Unzureichende Rechte</msg>
  <msg key="lt_interval_select_per_c">%interval_select% pro Spalte</msg>
  <msg key="lt_Intranet_Absence_Type">Intranet Abwesenheitsart</msg>
  <msg key="lt_is_required_Describe_">ist erforderlich. Beschreiben Sie den Zweck der Kosten und im Falle der Verwendung vom eigenen Auto, die Anzahl der Kilometer.</msg>
  <msg key="lt_It_looks_like_youre_t">Es sieht so aus als würden Sie versuchen die Stunden von jemand anders zu bearbeiten. Leider sind Sie nicht berechtigt das zu tun. Sie können Ihre %own_hours_link% bearbeiten wenn Sie wollen</msg>
  <msg key="lt_Log_hours_for_a_diffe">Stunden erfassen für einen anderen Tag</msg>
  <msg key="lt_Log_hours_for_a_diffe_1">Melde Stunden für eine andere Woche</msg>
  <msg key="lt_Log_hours_on_selected">Melde Stunden in den ausgewählten Projekten</msg>
  <msg key="lt_Log_your_log_hours_li">Erfassen sie ihre %log_hours_link% Stunden</msg>
  <msg key="lt_Log_your_log_hours_li_1">Erfassen sie ihre %log_hours_link% Stunden</msg>
  <msg key="lt_MOST_COMMON_EXCHANGE_">HÄUFIGSTE WECHSELKURSE</msg>
  <msg key="lt_new_instructions_here">Neue Anweisungen hier.</msg>
  <msg key="lt_No_hours_for_this_wee">Keine Stunden für diese Woche</msg>
  <msg key="lt_No_hours_logged_in_th">Keine Stunden angemeldet in den letzten %number_days_string%</msg>
  <msg key="lt_No_hours_logged_on_pr">Keine Stunden aufgezeichnet in %project_name% zwischen %from% und %ending%</msg>
  <msg key="lt_No_time_logged_on_any">Keine Zeit aufgezeichnet zu Projekten</msg>
  <msg key="lt_No_units_have_been_lo">Keine Einheiten wurden protokolliert durch irgendeinen Benutzer</msg>
  <msg key="lt_num_hours_hours_logge">%num_hours% Stunde(n) protokolliert in den letzten %number_days_string%:</msg>
  <msg key="lt_Please_notify_your_ma">Bitte informieren Sie Ihren Vorgesetzten oder Systemadministrator.</msg>
  <msg key="lt_Please_select_a_proje">Bitte ein Projekt wählen</msg>
  <msg key="lt_Rate_Per_Km_Spain_02_">Preis pro km Spanien: 0,2 EUR; Frankreich: 0,3 Eur</msg>
  <msg key="lt_REMEMBER_total_of_10_">ACHTUNG: Insgesamt 10 Einheiten pro Tag, alle Tage!!! (keine Wochenenden)</msg>
  <msg key="lt_Return_to_previous_pa">Zurück zur vorigen Seite</msg>
  <msg key="lt_See_the_breakdown_by_">Stundenbericht pro Person</msg>
  <msg key="lt_Select_the_proyects_y">Wählen Sie die Projekte, die Sie senden wollen:</msg>
  <msg key="lt_Show_only_projects_wi">Zeige nur Projekte mit den erforderlichen Bericht?</msg>
  <msg key="lt_Starting_September_20">Ab September 2002 wird eine neues Zeit Einsatz Protokollierungssytem verwendet. Bitte lesen Sie die</msg>
  <msg key="lt_There_are_currently_n">Es wurden für die Suchkriterien keine Einträge gefunden</msg>
  <msg key="lt_There_are_currently_n_1">Derzeit gibt es keine Projekte für Sie, um Ihre Stunden zu protokollieren.</msg>
  <msg key="lt_There_are_no_projects">Es gibt keine Projekte, um Stunden hinzuzufügen.</msg>
  <msg key="lt_There_was_an_error_in">Es war ein Fehler in Ihrer Eingabe</msg>
  <msg key="lt_There_was_an_unexpect">Es war ein unerwarteter Fehler in der CASEX Datenbank</msg>
  <msg key="lt_Timeline_for_project_">Zeitschiene für %project_name% </msg>
  <msg key="lt_To_send_proyect_infor">Klicken sie hier um die Projektinformationen per E-Mail zu verschicken</msg>
  <msg key="lt_To_send_this_informat">Um diese Informationen per Email zu versenden, klicken Sie bitte in der Microsoft Internet Explorer Menüleiste auf 'Datei-&gt; Senden-&gt; Seite durch E-Mail...' (diese Option ignoriert die Werte die Sie in den Filter ausgewählt haben)</msg>
  <msg key="lt_Today_you_didnt_log_y">Sie haben heute noch keine Stunden erfaßt!</msg>
  <msg key="lt_Total_Company_visa_Eu">Summe Euros (Firmenkreditkarte)</msg>
  <msg key="lt_total_hours_hours_bet">%total_hours% Stunden zwischen %first_day_str% und %last_day_str% </msg>
  <msg key="lt_total_hours_units_bet">%total_hours% Stunden zwischen %first_day_str% und %last_day_str% </msg>
  <msg key="lt_total_hours_units_bet_1">%total_hours% Stunden zwischen %first_day_str% und %last_day_str% </msg>
  <msg key="lt_Total_not_company_vis">Summe Euros (Firmenkreditkarte)</msg>
  <msg key="lt_Unexpected_Database_E">Unerwarteter Datenbankfehler</msg>
  <msg key="lt_Units_on_all_projects">Einheiten auf allen Projekten</msg>
  <msg key="lt_Units_on_item_by_user">Einheiten auf &quot;%item%&quot; von %user_name% </msg>
  <msg key="lt_User_user_id_does_not">Benutzer #%user_id% existiert nicht</msg>
  <msg key="lt_User_user_id_does_not_1">Benutzer #%user_id% existiert nicht. Bitte gehen sie zurück und probieren sie noch einmal</msg>
  <msg key="lt_View_hours_logged_by_">Erfaßte Stunden pro Projektmitglied</msg>
  <msg key="lt_View_hours_logged_dur">Alle erfaßten Stunden der letzen Woche</msg>
  <msg key="lt_View_the_hours_logged">Erfaßte Stunden einer anderen Person</msg>
  <msg key="lt_View_time_spent_on_al">Alle erfaßte Stunden in allen Projekten</msg>
  <msg key="lt_View_your_hours_on_al">Ihre Stunden in allen Projekten</msg>
  <msg key="lt_We_couldnt_find_absen">Wir können die Abwesenheitsnummer %absence_id% nicht finden; Ohh... Es kann etwas nicht mit unserer Seite stimmen!</msg>
  <msg key="lt_We_couldnt_find_the_u">Es wurde keine Benutzer Nummer%user_id% in der Datenbank gefunden. Bitte Sicherungskopie erstellen, neu laden und erneut versuchen. </msg>
  <msg key="lt_We_got_an_error_delet">Fehler beim Löschen dieser Transaktion</msg>
  <msg key="lt_We_got_an_error_delet_1">Fehler beim löschen des Datensatzes</msg>
  <msg key="lt_We_got_an_error_inser">Fehler beim Einfügen der Transaktion</msg>
  <msg key="lt_Weekly_total_by_user_">Wöchentliche Summe von %user_name% </msg>
  <msg key="lt_You_cant_edit_someone">Sie können nicht die Stunden von jemand anders bearbeiten</msg>
  <msg key="lt_You_dont_have_suffici">Sie haben keine ausreichenden Privielgien um Abwesenheiten zu sehen.</msg>
  <msg key="lt_You_dont_have_suffici_1">Sie verfügen über nicht ausreichende Berechtigungen zum Ändern dieser Abwesenheit.</msg>
  <msg key="lt_You_have_loged_total_">Sie haben %total_hours_str% auf diesem Projekt erfaßt</msg>
  <msg key="lt_You_have_no_rights_to">Sie haben unzureichende Berechtigungen, um diese Seite zu sehen.</msg>
  <msg key="lt_You_havent_logged_you">Sie haben in der letzen Woche keine Stunden erfaßt, bitte %log_them_now_link% tun Sie das jetzt</msg>
  <msg key="lt_You_logged_num_hours_">Sie haben %num_hours% Stunden in den letzten 7 Tagen erfaßt.</msg>
  <msg key="M">M</msg>
  <msg key="Mar">März</msg>
  <msg key="March">März</msg>
  <msg key="May">Mai</msg>
  <msg key="Mine">Meine</msg>
  <msg key="Monday">Montag</msg>
  <msg key="Month">Monat</msg>
  <msg key="More_currencies">Weitere Währungen</msg>
  <msg key="N">N</msg>
  <msg key="Name">Name</msg>
  <msg key="New_Absence">Neue Abwesenheit</msg>
  <msg key="New_Absence_Type">Neue %absence_type% </msg>
  <msg key="New_Bank_Holiday">Neuer Feiertag</msg>
  <msg key="New_Personal_Absence">Neue Abwesenheit (privat)</msg>
  <msg key="New_Sick_Leave">Neue Abwesenheit (Krankheit)</msg>
  <msg key="New_Travel_Absence">Neue Abwesenheit (Reise)</msg>
  <msg key="New_Vacation_Absence">Neu Abwesenheit (Urlaub)</msg>
  <msg key="Next_Month">Nächster Monat</msg>
  <msg key="No_Data_found">Keine Daten gefunden</msg>
  <msg key="No_hours_logged">Keine Stunden erfaßt</msg>
  <msg key="No_Users_found">Kein Benutzer gefunden.</msg>
  <msg key="No_users_found">Keine Benutzer gefunden.</msg>
  <msg key="none">kein</msg>
  <msg key="Not_member_of_project">Sie sind nicht Mitglied dieses Projekts.</msg>
  <msg key="Not_Member_of_Projects">Sie sind in keinem derzeit offenen Projekt Mitglied.</msg>
  <msg key="Notes">Notizen</msg>
  <msg key="Notice">Notiz</msg>
  <msg key="Notification_Subject_Notify_Applicant_Absence_Approved">Ihr Antrag auf Abwesenheit</msg>
  <msg key="Notification_Body_Notify_Applicant_Absence_Approved">Ihrem Antrag wurde stattgegeben:</msg>
  <msg key="Notification_Subject_Notify_Applicant_Absence_Not_Approved">Ihr Antrag auf Abwesenheit</msg>
  <msg key="Notification_Body_Notify_Applicant_Absence_Not_Approved">Ihrem Antrag konnte nicht stattgegeben werden:</msg>
  <msg key="Nov">Nov</msg>
  <msg key="November">November</msg>
  <msg key="O">O</msg>
  <msg key="Oct">Okt</msg>
  <msg key="October">Oktober</msg>
  <msg key="One_employee">Ein Mitarbeiter</msg>
  <msg key="One_project">Ein Projekt</msg>
  <msg key="Other_Options">Andere Optionen</msg>
  <msg key="own_hours">eigene Stunden</msg>
  <msg key="P">P</msg>
  <msg key="Paid_by_Co">Von der Firma bereits bezahlt?</msg>
  <msg key="Past">Vergangen</msg>
  <msg key="Percentage">Prozent</msg>
  <msg key="Printer_Friendly">Druckerfreundliche Version</msg>
  <msg key="Project">Projekt</msg>
  <msg key="Project_br_Name">Projekt
name</msg>
  <msg key="Project_History">Projekthistorie</msg>
  <msg key="Project_name">Projektname</msg>
  <msg key="Project_Summaries">Projektzusammenfassung</msg>
  <msg key="Project_units">Projekteinheiten</msg>
  <msg key="Q">Q</msg>
  <msg key="R">R</msg>
  <msg key="Rate_Per_Km">Rate pro Km.</msg>
  <msg key="Rates">Rate</msg>
  <msg key="Real">Echt</msg>
  <msg key="Restrict_date">Beschränkungsdatum</msg>
  <msg key="S">S</msg>
  <msg key="Saturday">Samstag</msg>
  <msg key="Save">Speichern</msg>
  <msg key="Select_a_company">Wählen Sie eine Firma</msg>
  <msg key="select_a_company">Wählen Sie eine Firma</msg>
  <msg key="Select_a_task">Wählen Sie eine Aufgabe</msg>
  <msg key="select_a_task">Wählen Sie eine Aufgabe</msg>
  <msg key="Select_an_expense">Wählen Sie Kosten</msg>
  <msg key="select_an_expense">Wählen Sie Kosten</msg>
  <msg key="Send">Senden</msg>
  <msg key="Send_From">Senden von</msg>
  <msg key="Send_project_report">Projektreport senden</msg>
  <msg key="Send_To">Senden an</msg>
  <msg key="Sep">Sep</msg>
  <msg key="September">September</msg>
  <msg key="Show_one">Anzeigen</msg>
  <msg key="Show_Users">Benutzer anzeigen</msg>
  <msg key="Start_Date">Startdatum</msg>
  <msg key="Starting">Start</msg>
  <msg key="Status">Status</msg>
  <msg key="submit">Bestätigen</msg>
  <msg key="Summary">Zusammenfassung</msg>
  <msg key="Summary_by_date">Zusammenfassung nach Datum</msg>
  <msg key="Sunday">Sonntag</msg>
  <msg key="T">T</msg>
  <msg key="Tasks">Aufgaben</msg>
  <msg key="The_week_for_user">Die Woche für %user_name_from_search%</msg>
  <msg key="this_day_entry">Einträge von heute</msg>
  <msg key="Thursday">Donnerstag</msg>
  <msg key="Timescale">Zeitskala</msg>
  <msg key="Timesheet">Zeiterfassung</msg>
  <msg key="Timesheet_for_user_name">Zeiterfassung für %user_name%</msg>
  <msg key="Timesheet_Summary">Zusammenfassung Stunden</msg>
  <msg key="to">an</msg>
  <msg key="Today">Heute</msg>
  <msg key="Tools">Werkzeuge</msg>
  <msg key="Total">Gesamtsumme</msg>
  <msg key="Total_1">Gesamtsumme</msg>
  <msg key="Total_Amount">Gesamtsumme</msg>
  <msg key="Total_Euros">Gesamtsumme EUR</msg>
  <msg key="Tuesday">Dienstag</msg>
  <msg key="Type">Typ</msg>
  <msg key="U">U</msg>
  <msg key="Unexpected_Error">Unerwarteter Fehler</msg>
  <msg key="Units">Einheiten</msg>
  <msg key="Units_by_user_name">Erfaßte Stunden von %user_name% </msg>
  <msg key="Units_on_one_project">Einheiten auf einem Projekt</msg>
  <msg key="User">Benutzer</msg>
  <msg key="User_does_not_exist">Der Benutzer existiert nicht</msg>
  <msg key="user_not_logged_in">Benutzer nicht angemeldet</msg>
  <msg key="Users">Benutzer</msg>
  <msg key="V">V</msg>
  <msg key="View">Sicht</msg>
  <msg key="View_Absence">Abwesehnheiten zeigen</msg>
  <msg key="View_all_Absences">Alle Abwesenheiten anzeigen</msg>
  <msg key="View_employees_hours">Mitarbeiter Stunden anzeigen</msg>
  <msg key="View_employees_units">Mitarbeiter Stunden anzeigen</msg>
  <msg key="View_History">Historie anzeigen</msg>
  <msg key="Visa_Amount">Kreditkarten Betrag</msg>
  <msg key="W">W</msg>
  <msg key="Wednesday">Mittwoch</msg>
  <msg key="Week">Woche</msg>
  <msg key="Week_total">Woche total</msg>
  <msg key="Week_total_1">Woche gesamt</msg>
  <msg key="Weekly_hours">Wöchentliche Stunden</msg>
  <msg key="Work_done">Geleistete Arbeit</msg>
  <msg key="Worked_Day">Arbeitstag</msg>
  <msg key="X">X</msg>
  <msg key="Y">Y</msg>
  <msg key="You_need_to_log_hours">
  Sie haben bisher lediglich %num_hours% Stunden Arbeitszeit %absences_hours_message%
  erfasst von erforderlichen %expected_hours% Stunden in den letzten %num_days% Tagen.
  Bitte aktualisieren Sie ihre Stunden oder setzen Sie sich mit Ihrem Vorgesetzten in Verbindung.
  </msg>
  <msg key="Your_hours">Ihre Stunden</msg>
  <msg key="Your_workspace">Ihr Arbeitsbereich</msg>
</message_catalog>
